advanced_input/__init__.py
advanced_input/constants.py
advanced_input/input.py
advanced_input/inputExtention.c
advanced_input/inputExtention.dll
advanced_input/inputExtention.so
advanced_input-0.2.2.dist-info/LICENSE
advanced_input-0.2.2.dist-info/METADATA
advanced_input-0.2.2.dist-info/WHEEL
advanced_input-0.2.2.dist-info/top_level.txt
advanced_input-0.2.2.dist-info/RECORD
