Metadata-Version: 2.1
Name: advanced_input
Version: 0.2.2
Summary: IO Extention
Home-page: https://github.com/NightKey/advanced-input
Author: Janthó Dávid
Author-email: davidjantho@gmail.com
Project-URL: Bug Tracker, https://github.com/NightKey/advanced-input/issues
Classifier: Development Status :: 4 - Beta
Classifier: Programming Language :: Python :: 3
Classifier: License :: Freeware
Classifier: Operating System :: OS Independent
Requires-Python: >=3.7
License-File: LICENSE
